jsontrips/__init__.py
jsontrips/code.py
jsontrips/data/featurelists.json
jsontrips/data/featuretypes.json
jsontrips/data/golist.txt
jsontrips/data/lexicon_lf.json
jsontrips/data/ontology.json
jsontrips/data/stoplist.txt
jsontrips/data/syntax_templates.json
jsontrips/data/words.json
jsontrips-0.1.50.dist-info/LICENSE
jsontrips-0.1.50.dist-info/METADATA
jsontrips-0.1.50.dist-info/WHEEL
jsontrips-0.1.50.dist-info/top_level.txt
jsontrips-0.1.50.dist-info/RECORD
