Metadata-Version: 2.1
Name: jsontrips
Version: 0.1.50
Summary: A basic package
Home-page: https://github.com/mrmechko/jsontrips
Author: Rik
Author-email: rbose@cs.rochester.edu
License: UNKNOWN
Platform: UNKNOWN
Classifier: Programming Language :: Python :: 3
Classifier: License :: OSI Approved :: GNU General Public License v2 or later (GPLv2+)
Classifier: Operating System :: OS Independent
